Adders/full_adder.v
module full_adder (
    input a,
    input b,
    input cin,
    output sum,
    output cout
);

    // Full Adder logic using dataflow modeling
    assign sum = a ^ b ^ cin;
    assign cout = (a & b) | (b & cin) | (cin & a);

endmodule

Adders/full_adder_tb.v
module full_adder_tb;

    // Inputs (reg) aur Outputs (wire) declare karo
    reg a;
    reg b;
    reg cin;
    wire sum;
    wire cout;

    // Design module ko instantiate karo
    full_adder uut (
        .a(a),
        .b(b),
        .cin(cin),
        .sum(sum),
        .cout(cout)
    );

    initial begin
        // YE HAIN WO LINES JISSE GTKWAVE KHULEGA
        $dumpfile("full_adder.vcd"); // Ye file ka naam set karta hai
        $dumpvars(0, full_adder_tb); // Ye saare variables ka data dump karta hai

        // Truth table ke test cases
        a = 0; b = 0; cin = 0; #10;
        a = 0; b = 0; cin = 1; #10;
        a = 0; b = 1; cin = 0; #10;
        a = 0; b = 1; cin = 1; #10;
        a = 1; b = 0; cin = 0; #10;
        a = 1; b = 0; cin = 1; #10;
        a = 1; b = 1; cin = 0; #10;
        a = 1; b = 1; cin = 1; #10;

        // Simulation khatam karo
        $finish;
    end

endmodule

Adders/full_adder.vcd
$date
	Sun May 03 13:38:10 2026
$end
$version
	Icarus Verilog
$end
$timescale
	1s
$end
$scope module full_adder_tb $end
$var wire 1 ! sum $end
$var wire 1 " cout $end
$var reg 1 # a $end
$var reg 1 $ b $end
$var reg 1 % cin $end
$scope module uut $end
$var wire 1 # a $end
$var wire 1 $ b $end
$var wire 1 % cin $end
$var wire 1 " cout $end
$var wire 1 ! sum $end
$upscope $end
$upscope $end
$enddefinitions $end
$comment Show the parameter values. $end
$dumpall
$end
#0
$dumpvars
0%
0$
0#
0"
0!
$end
#10
1!
1%
#20
0%
1$
#30
1"
0!
1%
#40
0"
1!
0%
0$
1#
#50
1"
0!
1%
#60
0%
1$
#70
1!
1%
