Subtractors/full_subtractor.v
module full_subtractor (
    input a,
    input b,
    input bin,    // Borrow In
    output diff,  // Difference
    output bout   // Borrow Out
);

    // Full Subtractor logic using dataflow modeling
    assign diff = a ^ b ^ bin;
    assign bout = (~a & b) | (~(a ^ b) & bin);

endmodule

Subtractors/full_subtractor_tb.v
module full_subtractor_tb;

    // Inputs (reg) aur Outputs (wire) declare karo
    reg a;
    reg b;
    reg bin;
    wire diff;
    wire bout;

    // Design module ko instantiate karo
    full_subtractor uut (
        .a(a),
        .b(b),
        .bin(bin),
        .diff(diff),
        .bout(bout)
    );

    initial begin
        // GTKWAVE FILE GENERATE KARNE KE LIYE LINES
        $dumpfile("full_subtractor.vcd"); 
        $dumpvars(0, full_subtractor_tb); 

        // Truth table ke test cases (000 se 111 tak)
        a = 0; b = 0; bin = 0; #10;
        a = 0; b = 0; bin = 1; #10;
        a = 0; b = 1; bin = 0; #10;
        a = 0; b = 1; bin = 1; #10;
        a = 1; b = 0; bin = 0; #10;
        a = 1; b = 0; bin = 1; #10;
        a = 1; b = 1; bin = 0; #10;
        a = 1; b = 1; bin = 1; #10;

        // Simulation khatam karo
        $finish;
    end

endmodule

Subtractors/full_subtractor.vcd
$date
	Sun May 03 13:52:29 2026
$end
$version
	Icarus Verilog
$end
$timescale
	1s
$end
$scope module full_subtractor_tb $end
$var wire 1 ! diff $end
$var wire 1 " bout $end
$var reg 1 # a $end
$var reg 1 $ b $end
$var reg 1 % bin $end
$scope module uut $end
$var wire 1 # a $end
$var wire 1 $ b $end
$var wire 1 % bin $end
$var wire 1 " bout $end
$var wire 1 ! diff $end
$upscope $end
$upscope $end
$enddefinitions $end
$comment Show the parameter values. $end
$dumpall
$end
#0
$dumpvars
0%
0$
0#
0"
0!
$end
#10
1"
1!
1%
#20
0%
1$
#30
0!
1%
#40
0"
1!
0%
0$
1#
#50
0!
1%
#60
0%
1$
#70
1"
1!
1%
